[
  {
    "type": "post",
    "id": "post-id-1",
    "attributes": {
      "name": "First Post"
    },
    "relationships": {
      "comments": [
        { "type": "comment", "id": "post-id-1" }
      ]
    },
    "meta": {
      "errors": {},
      "changedAttributes": {},
      "isDeleted": false,
      "isLoaded": false,
      "isLoading": false,
      "isNew": false,
      "isReloading": false,
      "isSaving": false,
      "isValid": false
    }
  },
  {
    "type": "post",
    "id": "post-id-2",
    "attributes": {
      "name": "Second Post"
    },
    "relationships": {},
    "meta": {}
  }
]
